oss/oss_api.py
oss/pkg_info.py
oss/oss_util.py
oss/__init__.py
oss/oss_xml_handler.py
oss/oss_sample.py
oss-0.1.3.dist-info/METADATA
oss-0.1.3.dist-info/RECORD
oss-0.1.3.dist-info/top_level.txt
oss-0.1.3.dist-info/DESCRIPTION.rst
oss-0.1.3.dist-info/metadata.json
oss-0.1.3.dist-info/WHEEL
