Metadata-Version: 2.0
Name: oss
Version: 0.1.3
Summary: Command line tool for managing Aliyun Open Storage Service.
Home-page: http://oss.aliyun.com
Author: Aliyun OSS
Author-email: UNKNOWN
License: GPL version 2
Platform: UNKNOWN
